vector_database_loader/__init__.py
vector_database_loader/base_vector_db.py
vector_database_loader/document_processing_utils.py
vector_database_loader/milvus_vector_db.py
vector_database_loader/pinecone_vector_db.py
vector_database_loader-0.2.2.dist-info/LICENSE
vector_database_loader-0.2.2.dist-info/METADATA
vector_database_loader-0.2.2.dist-info/WHEEL
vector_database_loader-0.2.2.dist-info/RECORD
