Metadata-Version: 2.1
Name: vector-database-loader
Version: 0.2.2
Summary: A generalized tool for currating and loading content into vector databases
Home-page: https://medium.com/@dan.jam.kuhn/data-pipelines-for-rag-a-python-utility-for-populating-vector-databases-3f6c164756e9
License: MIT
Keywords: vector,database,loader,milvus,langchain,pinecone
Author: danjamk
Requires-Python: >=3.11,<3.13
Classifier: License :: OSI Approved :: MIT License
Classifier: Programming Language :: Python :: 3
Classifier: Programming Language :: Python :: 3.11
Classifier: Programming Language :: Python :: 3.12
Requires-Dist: colorama (>=0.4.6,<0.5.0)
Requires-Dist: docx2txt (>=0.8,<0.9)
Requires-Dist: google-api-python-client (>=2.160.0,<3.0.0)
Requires-Dist: google-auth-httplib2 (>=0.2.0,<0.3.0)
Requires-Dist: google-auth-oauthlib (>=1.2.1,<2.0.0)
Requires-Dist: langchain (>=0.3.17,<0.4.0)
Requires-Dist: langchain-community (>=0.3.16,<0.4.0)
Requires-Dist: langchain-milvus (>=0.1.8,<0.2.0)
Requires-Dist: langchain-openai (>=0.3.2,<0.4.0)
Requires-Dist: langchain-pinecone (>=0.2.2,<0.3.0)
Requires-Dist: pymilvus (>=2.5.4,<3.0.0)
Requires-Dist: python-dotenv (>=1.0.1,<2.0.0)
Requires-Dist: selenium (>=4.28.1,<5.0.0)
Requires-Dist: unstructured (>=0.16.17,<0.17.0)
Project-URL: Repository, https://github.com/danjamk/vector-database-loader
